{
  "info": {
    "name": "SpecQQ Chatbot Router API",
    "description": "Complete API collection for SpecQQ Chatbot Router System v1.0.0\n\nThis collection includes all 41 API endpoints organized by category:\n- Authentication (5 endpoints)\n- CQ Code Parsing (6 endpoints)\n- Statistics (4 endpoints)\n- Rules Management (7 endpoints)\n- Group Management (6 endpoints)\n- Message Logs (5 endpoints)\n- WebSocket (2 endpoints)\n- Health & Metrics (6 endpoints)\n\n**Setup Instructions:**\n1. Import this collection into Postman\n2. Import the environment file (SpecQQ-API.postman_environment.json)\n3. Run the 'Login' request first to obtain JWT token\n4. Token is automatically stored in environment variable and used for all subsequent requests\n\n**Authentication:**\nAll requests (except Login and Init Admin) require JWT Bearer token.\nToken expires after 24 hours.\n\n**Base URL:**\n- Development: http://localhost:8080/api\n- Production: Update {{base_url}} in environment\n\n**Version**: 1.0.0\n**Last Updated**: 2026-02-11",
    "schema": "https://schema.getpostman.com/json/collection/v2.1.0/collection.json",
    "_exporter_id": "specqq-v1"
  },
  "auth": {
    "type": "bearer",
    "bearer": [
      {
        "key": "token",
        "value": "{{jwt_token}}",
        "type": "string"
      }
    ]
  },
  "item": [
    {
      "name": "Authentication",
      "item": [
        {
          "name": "Login",
          "event": [
            {
              "listen": "test",
              "script": {
                "exec": [
                  "// Store JWT token in environment variable",
                  "if (pm.response.code === 200) {",
                  "    var jsonData = pm.response.json();",
                  "    pm.environment.set('jwt_token', jsonData.data.accessToken);",
                  "    pm.environment.set('token_expires_in', jsonData.data.expiresIn);",
                  "    console.log('JWT token stored successfully');",
                  "    console.log('Token expires in: ' + jsonData.data.expiresIn + ' seconds');",
                  "}",
                  "",
                  "// Validate response",
                  "pm.test('Status code is 200', function() {",
                  "    pm.response.to.have.status(200);",
                  "});",
                  "",
                  "pm.test('Response contains access token', function() {",
                  "    var jsonData = pm.response.json();",
                  "    pm.expect(jsonData.data).to.have.property('accessToken');",
                  "    pm.expect(jsonData.data).to.have.property('tokenType');",
                  "    pm.expect(jsonData.data.tokenType).to.eql('Bearer');",
                  "});"
                ],
                "type": "text/javascript"
              }
            }
          ],
          "request": {
            "auth": {
              "type": "noauth"
            },
            "method": "POST",
            "header": [
              {
                "key": "Content-Type",
                "value": "application/json"
              }
            ],
            "body": {
              "mode": "raw",
              "raw": "{\n  \"username\": \"{{admin_username}}\",\n  \"password\": \"{{admin_password}}\"\n}"
            },
            "url": {
              "raw": "{{base_url}}/auth/login",
              "host": ["{{base_url}}"],
              "path": ["auth", "login"]
            },
            "description": "Authenticate user and obtain JWT token.\n\n**Request Body:**\n- username: Admin username (default: admin)\n- password: Admin password (default: admin123)\n\n**Response:**\n- accessToken: JWT token (valid for 24 hours)\n- tokenType: Bearer\n- expiresIn: Token expiration time in seconds (86400)"
          },
          "response": []
        },
        {
          "name": "Get User Info",
          "event": [
            {
              "listen": "test",
              "script": {
                "exec": [
                  "pm.test('Status code is 200', function() {",
                  "    pm.response.to.have.status(200);",
                  "});",
                  "",
                  "pm.test('Response contains user info', function() {",
                  "    var jsonData = pm.response.json();",
                  "    pm.expect(jsonData.data).to.have.property('username');",
                  "    pm.expect(jsonData.data).to.have.property('role');",
                  "});"
                ],
                "type": "text/javascript"
              }
            }
          ],
          "request": {
            "method": "GET",
            "header": [],
            "url": {
              "raw": "{{base_url}}/auth/user-info",
              "host": ["{{base_url}}"],
              "path": ["auth", "user-info"]
            },
            "description": "Get current authenticated user information.\n\n**Requires:** JWT Bearer token\n\n**Response:**\n- username: User's username\n- role: User's role (ADMIN)\n- permissions: List of permissions"
          },
          "response": []
        },
        {
          "name": "Refresh Token",
          "event": [
            {
              "listen": "test",
              "script": {
                "exec": [
                  "if (pm.response.code === 200) {",
                  "    var jsonData = pm.response.json();",
                  "    pm.environment.set('jwt_token', jsonData.data.accessToken);",
                  "    console.log('JWT token refreshed successfully');",
                  "}"
                ],
                "type": "text/javascript"
              }
            }
          ],
          "request": {
            "method": "POST",
            "header": [],
            "url": {
              "raw": "{{base_url}}/auth/refresh",
              "host": ["{{base_url}}"],
              "path": ["auth", "refresh"]
            },
            "description": "Refresh JWT token before expiration.\n\n**Requires:** Valid JWT Bearer token\n\n**Response:**\n- accessToken: New JWT token\n- expiresIn: New expiration time"
          },
          "response": []
        },
        {
          "name": "Logout",
          "event": [
            {
              "listen": "test",
              "script": {
                "exec": [
                  "if (pm.response.code === 200) {",
                  "    pm.environment.unset('jwt_token');",
                  "    console.log('Logged out successfully, token cleared');",
                  "}"
                ],
                "type": "text/javascript"
              }
            }
          ],
          "request": {
            "method": "POST",
            "header": [],
            "url": {
              "raw": "{{base_url}}/auth/logout",
              "host": ["{{base_url}}"],
              "path": ["auth", "logout"]
            },
            "description": "Logout and invalidate JWT token.\n\n**Requires:** JWT Bearer token\n\n**Effect:** Token is added to blacklist and cannot be reused"
          },
          "response": []
        },
        {
          "name": "Initialize Admin User",
          "request": {
            "auth": {
              "type": "noauth"
            },
            "method": "POST",
            "header": [
              {
                "key": "Content-Type",
                "value": "application/json"
              }
            ],
            "body": {
              "mode": "raw",
              "raw": "{\n  \"username\": \"admin\",\n  \"password\": \"admin123\"\n}"
            },
            "url": {
              "raw": "{{base_url}}/auth/init-admin",
              "host": ["{{base_url}}"],
              "path": ["auth", "init-admin"]
            },
            "description": "Initialize admin user on first-time setup.\n\n**Note:** This endpoint only works if no admin user exists.\nUse this for initial system setup.\n\n**Request Body:**\n- username: Admin username\n- password: Admin password (min 6 characters)"
          },
          "response": []
        }
      ],
      "description": "Authentication and user management endpoints"
    },
    {
      "name": "CQ Code Parsing",
      "item": [
        {
          "name": "Parse CQ Codes",
          "request": {
            "method": "POST",
            "header": [
              {
                "key": "Content-Type",
                "value": "application/json"
              }
            ],
            "body": {
              "mode": "raw",
              "raw": "{\n  \"message\": \"Hello[CQ:face,id=123]World[CQ:image,file=test.jpg]\"\n}"
            },
            "url": {
              "raw": "{{base_url}}/cqcode/parse",
              "host": ["{{base_url}}"],
              "path": ["cqcode", "parse"]
            },
            "description": "Parse CQ codes from message and extract structured data.\n\n**Request Body:**\n- message: Message text containing CQ codes\n\n**Response:**\nArray of CQCode objects:\n- type: CQ code type (face, image, at, reply, record, video, other)\n- params: Key-value parameters\n- rawText: Original CQ code text\n\n**Example:**\n```json\n[\n  {\n    \"type\": \"face\",\n    \"params\": {\"id\": \"123\"},\n    \"rawText\": \"[CQ:face,id=123]\"\n  }\n]\n```"
          },
          "response": []
        },
        {
          "name": "Strip CQ Codes",
          "request": {
            "method": "POST",
            "header": [
              {
                "key": "Content-Type",
                "value": "application/json"
              }
            ],
            "body": {
              "mode": "raw",
              "raw": "{\n  \"message\": \"Hello[CQ:face,id=123]World\"\n}"
            },
            "url": {
              "raw": "{{base_url}}/cqcode/strip",
              "host": ["{{base_url}}"],
              "path": ["cqcode", "strip"]
            },
            "description": "Remove all CQ codes from message, leaving only plain text.\n\n**Request Body:**\n- message: Message text with CQ codes\n\n**Response:**\n- strippedMessage: Plain text without CQ codes"
          },
          "response": []
        },
        {
          "name": "Validate CQ Code",
          "request": {
            "method": "POST",
            "header": [
              {
                "key": "Content-Type",
                "value": "application/json"
              }
            ],
            "body": {
              "mode": "raw",
              "raw": "{\n  \"cqcode\": \"[CQ:face,id=123]\"\n}"
            },
            "url": {
              "raw": "{{base_url}}/cqcode/validate",
              "host": ["{{base_url}}"],
              "path": ["cqcode", "validate"]
            },
            "description": "Validate CQ code syntax and parse if valid.\n\n**Request Body:**\n- cqcode: Single CQ code to validate\n\n**Response:**\n- valid: true/false\n- parsed: Parsed CQCode object (if valid)\n- error: Error message (if invalid)"
          },
          "response": []
        },
        {
          "name": "Get CQ Code Types",
          "request": {
            "method": "GET",
            "header": [],
            "url": {
              "raw": "{{base_url}}/cqcode/types",
              "host": ["{{base_url}}"],
              "path": ["cqcode", "types"]
            },
            "description": "Get list of supported CQ code types.\n\n**Response:**\nArray of type strings:\n- face\n- image\n- at\n- reply\n- record\n- video\n- other"
          },
          "response": []
        },
        {
          "name": "Get Predefined Patterns",
          "request": {
            "method": "GET",
            "header": [],
            "url": {
              "raw": "{{base_url}}/cqcode/patterns",
              "host": ["{{base_url}}"],
              "path": ["cqcode", "patterns"]
            },
            "description": "Get predefined CQ code regex patterns for rule configuration.\n\n**Response:**\nArray of CQCodePattern objects:\n- id: Pattern identifier\n- type: CQ code type\n- label: Chinese display name\n- pattern: Regex pattern\n- description: Pattern description\n- paramFilters: Parameter filters (if applicable)"
          },
          "response": []
        },
        {
          "name": "Validate Pattern",
          "request": {
            "method": "POST",
            "header": [
              {
                "key": "Content-Type",
                "value": "application/json"
              }
            ],
            "body": {
              "mode": "raw",
              "raw": "{\n  \"pattern\": \"\\\\[CQ:face,id=(\\\\d+)\\\\]\"\n}"
            },
            "url": {
              "raw": "{{base_url}}/cqcode/patterns/validate",
              "host": ["{{base_url}}"],
              "path": ["cqcode", "patterns", "validate"]
            },
            "description": "Validate custom regex pattern for CQ code matching.\n\n**Request Body:**\n- pattern: Regex pattern to validate\n\n**Response:**\n- valid: true/false\n- exampleMatches: Array of example matches (if valid)\n- error: Error message (if invalid)"
          },
          "response": []
        }
      ],
      "description": "CQ code parsing and pattern management"
    },
    {
      "name": "Statistics",
      "item": [
        {
          "name": "Calculate Statistics",
          "request": {
            "method": "POST",
            "header": [
              {
                "key": "Content-Type",
                "value": "application/json"
              }
            ],
            "body": {
              "mode": "raw",
              "raw": "{\n  \"message\": \"Hello[CQ:face,id=123]World[CQ:image,file=test.jpg][CQ:face,id=456]\"\n}"
            },
            "url": {
              "raw": "{{base_url}}/statistics/calculate",
              "host": ["{{base_url}}"],
              "path": ["statistics", "calculate"]
            },
            "description": "Calculate CQ code statistics from message.\n\n**Request Body:**\n- message: Message text with CQ codes\n\n**Response:**\n- totalCount: Total number of CQ codes\n- countByType: Map of type to count\n- uniqueTypes: Array of unique types found"
          },
          "response": []
        },
        {
          "name": "Format Statistics",
          "request": {
            "method": "POST",
            "header": [
              {
                "key": "Content-Type",
                "value": "application/json"
              }
            ],
            "body": {
              "mode": "raw",
              "raw": "{\n  \"totalCount\": 3,\n  \"countByType\": {\n    \"face\": 2,\n    \"image\": 1\n  },\n  \"uniqueTypes\": [\"face\", \"image\"]\n}"
            },
            "url": {
              "raw": "{{base_url}}/statistics/format",
              "host": ["{{base_url}}"],
              "path": ["statistics", "format"]
            },
            "description": "Format statistics with Chinese labels.\n\n**Request Body:**\nMessageStatistics object\n\n**Response:**\n- formatted: Chinese formatted string (e.g., \"表情×2, 图片×1\")\n- totalCount: Total count\n- countByType: Original count map"
          },
          "response": []
        },
        {
          "name": "Calculate and Format",
          "request": {
            "method": "POST",
            "header": [
              {
                "key": "Content-Type",
                "value": "application/json"
              }
            ],
            "body": {
              "mode": "raw",
              "raw": "{\n  \"message\": \"Hello[CQ:face,id=123]World[CQ:image,file=test.jpg]\"\n}"
            },
            "url": {
              "raw": "{{base_url}}/statistics/calculate-and-format",
              "host": ["{{base_url}}"],
              "path": ["statistics", "calculate-and-format"]
            },
            "description": "Calculate statistics and format in one request.\n\n**Request Body:**\n- message: Message text with CQ codes\n\n**Response:**\n- formatted: Chinese formatted string\n- totalCount: Total count\n- countByType: Count map"
          },
          "response": []
        },
        {
          "name": "Test Statistics",
          "request": {
            "method": "POST",
            "header": [
              {
                "key": "Content-Type",
                "value": "application/json"
              }
            ],
            "body": {
              "mode": "raw",
              "raw": "{\n  \"message\": \"Hello[CQ:face,id=123]World[CQ:image,file=test.jpg]\",\n  \"expectedCount\": 2\n}"
            },
            "url": {
              "raw": "{{base_url}}/statistics/test",
              "host": ["{{base_url}}"],
              "path": ["statistics", "test"]
            },
            "description": "Test statistics calculation against expected count.\n\n**Request Body:**\n- message: Message text\n- expectedCount: Expected total count\n\n**Response:**\n- passed: true/false\n- actualCount: Calculated count\n- expectedCount: Expected count"
          },
          "response": []
        }
      ],
      "description": "Message statistics and CQ code analysis"
    },
    {
      "name": "Rules Management",
      "item": [
        {
          "name": "List Rules",
          "request": {
            "method": "GET",
            "header": [],
            "url": {
              "raw": "{{base_url}}/rules?page=1&size=10&enabled=true",
              "host": ["{{base_url}}"],
              "path": ["rules"],
              "query": [
                {
                  "key": "page",
                  "value": "1",
                  "description": "Page number (starts from 1)"
                },
                {
                  "key": "size",
                  "value": "10",
                  "description": "Page size (max 100)"
                },
                {
                  "key": "enabled",
                  "value": "true",
                  "description": "Filter by enabled status (optional)"
                },
                {
                  "key": "matchType",
                  "value": "",
                  "description": "Filter by match type (optional)",
                  "disabled": true
                },
                {
                  "key": "ruleName",
                  "value": "",
                  "description": "Search by rule name (optional)",
                  "disabled": true
                }
              ]
            },
            "description": "List all rules with pagination and filters.\n\n**Query Parameters:**\n- page: Page number (default: 1)\n- size: Page size (default: 10, max: 100)\n- enabled: Filter by status (optional)\n- matchType: Filter by match type (optional)\n- ruleName: Search by name (optional)\n\n**Response:**\n- items: Array of rules\n- totalItems: Total count\n- totalPages: Total pages\n- currentPage: Current page number"
          },
          "response": []
        },
        {
          "name": "Create Rule",
          "request": {
            "method": "POST",
            "header": [
              {
                "key": "Content-Type",
                "value": "application/json"
              }
            ],
            "body": {
              "mode": "raw",
              "raw": "{\n  \"ruleName\": \"Welcome Message\",\n  \"description\": \"Greet new members\",\n  \"matchType\": \"KEYWORD\",\n  \"matchPattern\": \"hello\",\n  \"replyType\": \"TEXT\",\n  \"replyContent\": \"Hello {user}! Welcome to {group}!\",\n  \"priority\": 10,\n  \"enabled\": true\n}"
            },
            "url": {
              "raw": "{{base_url}}/rules",
              "host": ["{{base_url}}"],
              "path": ["rules"]
            },
            "description": "Create new message routing rule.\n\n**Request Body:**\n- ruleName: Rule name (required)\n- description: Description (optional)\n- matchType: KEYWORD | REGEX | EXACT | PREFIX | SUFFIX\n- matchPattern: Pattern to match (required)\n- replyType: TEXT | IMAGE | FORWARD\n- replyContent: Reply content (required)\n- priority: Execution priority (lower = higher priority)\n- enabled: Enable immediately (default: true)\n\n**Variables in replyContent:**\n- {user}: Sender's name\n- {group}: Group name\n- {$1}, {$2}: Regex capture groups"
          },
          "response": []
        },
        {
          "name": "Get Rule Details",
          "request": {
            "method": "GET",
            "header": [],
            "url": {
              "raw": "{{base_url}}/rules/1",
              "host": ["{{base_url}}"],
              "path": ["rules", "1"]
            },
            "description": "Get detailed information about a specific rule.\n\n**Path Parameters:**\n- id: Rule ID\n\n**Response:**\nComplete rule object with all fields"
          },
          "response": []
        },
        {
          "name": "Update Rule",
          "request": {
            "method": "PUT",
            "header": [
              {
                "key": "Content-Type",
                "value": "application/json"
              }
            ],
            "body": {
              "mode": "raw",
              "raw": "{\n  \"ruleName\": \"Welcome Message (Updated)\",\n  \"description\": \"Greet new members with emoji\",\n  \"matchType\": \"KEYWORD\",\n  \"matchPattern\": \"hello\",\n  \"replyType\": \"TEXT\",\n  \"replyContent\": \"Hello {user}! 👋 Welcome to {group}!\",\n  \"priority\": 10,\n  \"enabled\": true\n}"
            },
            "url": {
              "raw": "{{base_url}}/rules/1",
              "host": ["{{base_url}}"],
              "path": ["rules", "1"]
            },
            "description": "Update existing rule.\n\n**Path Parameters:**\n- id: Rule ID\n\n**Request Body:**\nSame as Create Rule (all fields required)"
          },
          "response": []
        },
        {
          "name": "Delete Rule",
          "request": {
            "method": "DELETE",
            "header": [],
            "url": {
              "raw": "{{base_url}}/rules/1",
              "host": ["{{base_url}}"],
              "path": ["rules", "1"]
            },
            "description": "Delete rule permanently.\n\n**Path Parameters:**\n- id: Rule ID\n\n**Warning:** This action cannot be undone."
          },
          "response": []
        },
        {
          "name": "Toggle Rule Status",
          "request": {
            "method": "PUT",
            "header": [],
            "url": {
              "raw": "{{base_url}}/rules/1/toggle",
              "host": ["{{base_url}}"],
              "path": ["rules", "1", "toggle"]
            },
            "description": "Enable or disable rule.\n\n**Path Parameters:**\n- id: Rule ID\n\n**Effect:** Toggles enabled status (true ↔ false)"
          },
          "response": []
        },
        {
          "name": "Test Rule",
          "request": {
            "method": "POST",
            "header": [
              {
                "key": "Content-Type",
                "value": "application/json"
              }
            ],
            "body": {
              "mode": "raw",
              "raw": "{\n  \"ruleId\": 1,\n  \"testMessage\": \"hello world\"\n}"
            },
            "url": {
              "raw": "{{base_url}}/rules/test",
              "host": ["{{base_url}}"],
              "path": ["rules", "test"]
            },
            "description": "Test rule matching without executing.\n\n**Request Body:**\n- ruleId: Rule ID to test\n- testMessage: Sample message\n\n**Response:**\n- matched: true/false\n- reply: Generated reply (if matched)\n- capturedGroups: Regex capture groups (if applicable)\n- processingTime: Matching time in milliseconds"
          },
          "response": []
        }
      ],
      "description": "Message routing rule management"
    },
    {
      "name": "Group Management",
      "item": [
        {
          "name": "List Groups",
          "request": {
            "method": "GET",
            "header": [],
            "url": {
              "raw": "{{base_url}}/groups",
              "host": ["{{base_url}}"],
              "path": ["groups"]
            },
            "description": "List all configured QQ groups.\n\n**Response:**\nArray of group objects:\n- id: Group ID\n- groupId: QQ group number\n- groupName: Friendly name\n- enabled: Status\n- ruleCount: Number of bound rules"
          },
          "response": []
        },
        {
          "name": "Get Group Details",
          "request": {
            "method": "GET",
            "header": [],
            "url": {
              "raw": "{{base_url}}/groups/1",
              "host": ["{{base_url}}"],
              "path": ["groups", "1"]
            },
            "description": "Get detailed information about a specific group.\n\n**Path Parameters:**\n- id: Group ID"
          },
          "response": []
        },
        {
          "name": "Toggle Group Status",
          "request": {
            "method": "PUT",
            "header": [],
            "url": {
              "raw": "{{base_url}}/groups/1/toggle",
              "host": ["{{base_url}}"],
              "path": ["groups", "1", "toggle"]
            },
            "description": "Enable or disable group.\n\n**Path Parameters:**\n- id: Group ID\n\n**Effect:** Toggles enabled status"
          },
          "response": []
        },
        {
          "name": "Get Group Rules",
          "request": {
            "method": "GET",
            "header": [],
            "url": {
              "raw": "{{base_url}}/groups/1/rules",
              "host": ["{{base_url}}"],
              "path": ["groups", "1", "rules"]
            },
            "description": "Get all rules bound to a group.\n\n**Path Parameters:**\n- id: Group ID\n\n**Response:**\nArray of rules bound to this group"
          },
          "response": []
        },
        {
          "name": "Bind Rule to Group",
          "request": {
            "method": "POST",
            "header": [
              {
                "key": "Content-Type",
                "value": "application/json"
              }
            ],
            "body": {
              "mode": "raw",
              "raw": "{\n  \"ruleId\": 5\n}"
            },
            "url": {
              "raw": "{{base_url}}/groups/1/rules",
              "host": ["{{base_url}}"],
              "path": ["groups", "1", "rules"]
            },
            "description": "Bind rule to group.\n\n**Path Parameters:**\n- id: Group ID\n\n**Request Body:**\n- ruleId: Rule ID to bind"
          },
          "response": []
        },
        {
          "name": "Unbind Rule from Group",
          "request": {
            "method": "DELETE",
            "header": [],
            "url": {
              "raw": "{{base_url}}/groups/1/rules/5",
              "host": ["{{base_url}}"],
              "path": ["groups", "1", "rules", "5"]
            },
            "description": "Unbind rule from group.\n\n**Path Parameters:**\n- id: Group ID\n- ruleId: Rule ID to unbind"
          },
          "response": []
        }
      ],
      "description": "QQ group configuration and rule binding"
    },
    {
      "name": "Message Logs",
      "item": [
        {
          "name": "List Message Logs",
          "request": {
            "method": "GET",
            "header": [],
            "url": {
              "raw": "{{base_url}}/logs?page=1&size=20&groupId=1&status=SUCCESS",
              "host": ["{{base_url}}"],
              "path": ["logs"],
              "query": [
                {
                  "key": "page",
                  "value": "1"
                },
                {
                  "key": "size",
                  "value": "20"
                },
                {
                  "key": "groupId",
                  "value": "1",
                  "description": "Filter by group (optional)"
                },
                {
                  "key": "status",
                  "value": "SUCCESS",
                  "description": "Filter by status (optional)"
                },
                {
                  "key": "startDate",
                  "value": "",
                  "description": "Start date (YYYY-MM-DD) (optional)",
                  "disabled": true
                },
                {
                  "key": "endDate",
                  "value": "",
                  "description": "End date (YYYY-MM-DD) (optional)",
                  "disabled": true
                }
              ]
            },
            "description": "List message logs with pagination and filters.\n\n**Query Parameters:**\n- page: Page number\n- size: Page size\n- groupId: Filter by group (optional)\n- status: SUCCESS | FAILED (optional)\n- startDate: Start date (optional)\n- endDate: End date (optional)"
          },
          "response": []
        },
        {
          "name": "Get Log Details",
          "request": {
            "method": "GET",
            "header": [],
            "url": {
              "raw": "{{base_url}}/logs/123",
              "host": ["{{base_url}}"],
              "path": ["logs", "123"]
            },
            "description": "Get detailed information about a specific message log.\n\n**Path Parameters:**\n- id: Log ID"
          },
          "response": []
        },
        {
          "name": "Export Logs (CSV)",
          "request": {
            "method": "GET",
            "header": [],
            "url": {
              "raw": "{{base_url}}/logs/export?startDate=2026-02-01&endDate=2026-02-11&format=csv",
              "host": ["{{base_url}}"],
              "path": ["logs", "export"],
              "query": [
                {
                  "key": "startDate",
                  "value": "2026-02-01"
                },
                {
                  "key": "endDate",
                  "value": "2026-02-11"
                },
                {
                  "key": "format",
                  "value": "csv"
                }
              ]
            },
            "description": "Export message logs as CSV file.\n\n**Query Parameters:**\n- startDate: Start date (YYYY-MM-DD)\n- endDate: End date (YYYY-MM-DD)\n- format: csv | json (default: csv)\n\n**Response:** File download"
          },
          "response": []
        },
        {
          "name": "Get Log Statistics",
          "request": {
            "method": "GET",
            "header": [],
            "url": {
              "raw": "{{base_url}}/logs/stats?startDate=2026-02-01&endDate=2026-02-11",
              "host": ["{{base_url}}"],
              "path": ["logs", "stats"],
              "query": [
                {
                  "key": "startDate",
                  "value": "2026-02-01"
                },
                {
                  "key": "endDate",
                  "value": "2026-02-11"
                }
              ]
            },
            "description": "Get message log statistics for date range.\n\n**Query Parameters:**\n- startDate: Start date\n- endDate: End date\n\n**Response:**\n- totalMessages: Total count\n- matchedMessages: Messages with rule match\n- unmatchedMessages: Messages without match\n- matchRate: Percentage of matched messages\n- topRules: Most triggered rules"
          },
          "response": []
        },
        {
          "name": "Get Message Trends",
          "request": {
            "method": "GET",
            "header": [],
            "url": {
              "raw": "{{base_url}}/logs/trends?startDate=2026-02-01&endDate=2026-02-11&interval=daily",
              "host": ["{{base_url}}"],
              "path": ["logs", "trends"],
              "query": [
                {
                  "key": "startDate",
                  "value": "2026-02-01"
                },
                {
                  "key": "endDate",
                  "value": "2026-02-11"
                },
                {
                  "key": "interval",
                  "value": "daily",
                  "description": "hourly | daily (default: daily)"
                }
              ]
            },
            "description": "Get message volume trends over time.\n\n**Query Parameters:**\n- startDate: Start date\n- endDate: End date\n- interval: hourly | daily\n\n**Response:**\nArray of data points with timestamp and count"
          },
          "response": []
        }
      ],
      "description": "Message log querying and export"
    },
    {
      "name": "Health & Metrics",
      "item": [
        {
          "name": "Health Check",
          "request": {
            "auth": {
              "type": "noauth"
            },
            "method": "GET",
            "header": [],
            "url": {
              "raw": "{{base_url}}/../actuator/health",
              "host": ["{{base_url}}"],
              "path": ["..", "actuator", "health"]
            },
            "description": "Check application health status.\n\n**No authentication required**\n\n**Response:**\n- status: UP | DOWN\n- components: Health of individual components (database, redis, etc.)"
          },
          "response": []
        },
        {
          "name": "Prometheus Metrics",
          "request": {
            "auth": {
              "type": "noauth"
            },
            "method": "GET",
            "header": [],
            "url": {
              "raw": "{{base_url}}/../actuator/prometheus",
              "host": ["{{base_url}}"],
              "path": ["..", "actuator", "prometheus"]
            },
            "description": "Get Prometheus metrics.\n\n**No authentication required**\n\n**Metrics include:**\n- cqcode_parse_total: Parse request count\n- cqcode_parse_duration_seconds: Parse duration histogram\n- cqcode_cache_hits_total: Cache hit count\n- cqcode_cache_misses_total: Cache miss count\n- http_server_requests: HTTP request metrics"
          },
          "response": []
        },
        {
          "name": "Application Info",
          "request": {
            "auth": {
              "type": "noauth"
            },
            "method": "GET",
            "header": [],
            "url": {
              "raw": "{{base_url}}/../actuator/info",
              "host": ["{{base_url}}"],
              "path": ["..", "actuator", "info"]
            },
            "description": "Get application information.\n\n**Response:**\n- app: Application name and version\n- build: Build information\n- git: Git commit information (if available)"
          },
          "response": []
        },
        {
          "name": "Metrics Summary",
          "request": {
            "auth": {
              "type": "noauth"
            },
            "method": "GET",
            "header": [],
            "url": {
              "raw": "{{base_url}}/../actuator/metrics",
              "host": ["{{base_url}}"],
              "path": ["..", "actuator", "metrics"]
            },
            "description": "Get list of available metrics.\n\n**Response:**\nArray of metric names"
          },
          "response": []
        },
        {
          "name": "Specific Metric",
          "request": {
            "auth": {
              "type": "noauth"
            },
            "method": "GET",
            "header": [],
            "url": {
              "raw": "{{base_url}}/../actuator/metrics/cqcode.parse.total",
              "host": ["{{base_url}}"],
              "path": ["..", "actuator", "metrics", "cqcode.parse.total"]
            },
            "description": "Get specific metric details.\n\n**Path Parameters:**\n- metricName: Name of the metric\n\n**Response:**\n- name: Metric name\n- measurements: Current values\n- availableTags: Available tag filters"
          },
          "response": []
        },
        {
          "name": "Environment Properties",
          "request": {
            "method": "GET",
            "header": [],
            "url": {
              "raw": "{{base_url}}/../actuator/env",
              "host": ["{{base_url}}"],
              "path": ["..", "actuator", "env"]
            },
            "description": "Get environment properties.\n\n**Requires:** JWT Bearer token (admin only)\n\n**Response:**\nApplication configuration and environment variables"
          },
          "response": []
        }
      ],
      "description": "Health checks and metrics endpoints"
    }
  ],
  "variable": [
    {
      "key": "base_url",
      "value": "http://localhost:8080/api",
      "type": "string"
    },
    {
      "key": "jwt_token",
      "value": "",
      "type": "string"
    },
    {
      "key": "admin_username",
      "value": "admin",
      "type": "string"
    },
    {
      "key": "admin_password",
      "value": "admin123",
      "type": "string"
    }
  ]
}
